[
  {
    "group_tag": "Group1",
    "description": "Production Group 1"
  },
  {
    "group_tag": "Group10",
    "description": "Production Group 10"
  },
  {
    "group_tag": "Group10-2",
    "description": "Production Group 10-2"
  },
  {
    "group_tag": "Group12",
    "description": "Production Group 12"
  },
  {
    "group_tag": "Group2",
    "description": "Production Group 2"
  },
  {
    "group_tag": "Group3",
    "description": "Production Group 3"
  },
  {
    "group_tag": "Group4",
    "description": "Production Group 4"
  },
  {
    "group_tag": "Group5",
    "description": "Production Group 5"
  },
  {
    "group_tag": "PHR-1",
    "description": "PHR Production Group 1"
  },
  {
    "group_tag": "PHR-2",
    "description": "PHR Production Group 2"
  },
  {
    "group_tag": "PHR-3",
    "description": "PHR Production Group 3"
  },
  {
    "group_tag": "PHR-4",
    "description": "PHR Production Group 4"
  },
  {
    "group_tag": "PHR-5",
    "description": "PHR Production Group 5"
  },
  {
    "group_tag": "PHR-6",
    "description": "PHR Production Group 6"
  },
  {
    "group_tag": "PHR-7",
    "description": "PHR Production Group 7"
  },
  {
    "group_tag": "PHR-8",
    "description": "PHR Production Group 8"
  },
  {
    "group_tag": "PHR-9",
    "description": "PHR Production Group 9"
  },
  {
    "group_tag": "Prod01",
    "description": "Production 01"
  },
  {
    "group_tag": "Prod03",
    "description": "Production 03"
  },
  {
    "group_tag": "Prod05",
    "description": "Production 05"
  },
  {
    "group_tag": "Prod07",
    "description": "Production 07"
  },
  {
    "group_tag": "Prod09",
    "description": "Production 09"
  },
  {
    "group_tag": "Prod15",
    "description": "Production 15"
  },
  {
    "group_tag": "Prod24",
    "description": "Production 24"
  },
  {
    "group_tag": "Prod25",
    "description": "Production 25"
  },
  {
    "group_tag": "Prod29",
    "description": "Production 29"
  },
  {
    "group_tag": "Prod30",
    "description": "Production 30"
  },
  {
    "group_tag": "Prod33",
    "description": "Production 33"
  },
  {
    "group_tag": "Prod34",
    "description": "Production 34"
  },
  {
    "group_tag": "Prod35",
    "description": "Production 35"
  },
  {
    "group_tag": "Prod36",
    "description": "Production 36"
  },
  {
    "group_tag": "Prod37",
    "description": "Production 37"
  },
  {
    "group_tag": "Prod38",
    "description": "Production 38"
  },
  {
    "group_tag": "Prod39",
    "description": "Production 39"
  },
  {
    "group_tag": "Prod43",
    "description": "Production 43"
  },
  {
    "group_tag": "Prod60",
    "description": "Production 60"
  },
  {
    "group_tag": "Prod61",
    "description": "Production 61"
  },
  {
    "group_tag": "Prod62",
    "description": "Production 62"
  },
  {
    "group_tag": "Prod63",
    "description": "Production 63"
  },
  {
    "group_tag": "Prod64",
    "description": "Production 64"
  },
  {
    "group_tag": "Prod65",
    "description": "Production 65"
  },
  {
    "group_tag": "Prod66",
    "description": "Production 66"
  },
  {
    "group_tag": "Prod67",
    "description": "Production 67"
  },
  {
    "group_tag": "Prod68",
    "description": "Production 68"
  },
  {
    "group_tag": "tcp70alpha",
    "description": "TCP 70 Alpha"
  },
  {
    "group_tag": "Sandbox-Group1",
    "description": "Sandbox Group 1"
  },
  {
    "group_tag": "Sandbox-Group10",
    "description": "Sandbox Group 10"
  },
  {
    "group_tag": "Sandbox-Group12",
    "description": "Sandbox Group 12"
  },
  {
    "group_tag": "Sandbox-Group3",
    "description": "Sandbox Group 3"
  },
  {
    "group_tag": "Sandbox-Group4",
    "description": "Sandbox Group 4"
  },
  {
    "group_tag": "Sandbox-Prismhr2",
    "description": "Sandbox Prism HR 2"
  },
  {
    "group_tag": "Sandbox-Prod05",
    "description": "Sandbox Production 05"
  },
  {
    "group_tag": "Sandbox-Prod33",
    "description": "Sandbox Production 33"
  },
  {
    "group_tag": "Sandbox-Prod36",
    "description": "Sandbox Production 36"
  },
  {
    "group_tag": "Sandbox-Prod37",
    "description": "Sandbox Production 37"
  },
  {
    "group_tag": "Sandbox-Prod50",
    "description": "Sandbox Production 50"
  },
  {
    "group_tag": "Sandbox2-Prod37",
    "description": "Sandbox 2 Production 37"
  }
]
